yadisk_fetch.py
yadisk_fetch-0.1.3.dist-info/METADATA
yadisk_fetch-0.1.3.dist-info/WHEEL
yadisk_fetch-0.1.3.dist-info/entry_points.txt
yadisk_fetch-0.1.3.dist-info/top_level.txt
yadisk_fetch-0.1.3.dist-info/RECORD
