Metadata-Version: 2.4
Name: yadisk-fetch
Version: 0.1.3
Summary: Download Yandex.Disk folders easily by faking mobile browser headers
Author: YourName
Classifier: Programming Language :: Python :: 3
Classifier: License :: OSI Approved :: MIT License
Classifier: Operating System :: OS Independent
Requires-Python: >=3.6
Requires-Dist: requests
Dynamic: author
Dynamic: classifier
Dynamic: description
Dynamic: description-content-type
Dynamic: requires-dist
Dynamic: requires-python
Dynamic: summary
